jsfinder2/__init__.py
jsfinder2/__main__.py
jsfinder2/settings.py
jsfinder2/lib/__init__.py
jsfinder2/lib/jsfinder2.py
jsfinder2/lib/utils.py
JSFinder2-0.2.dist-info/LICENSE
JSFinder2-0.2.dist-info/METADATA
JSFinder2-0.2.dist-info/WHEEL
JSFinder2-0.2.dist-info/entry_points.txt
JSFinder2-0.2.dist-info/top_level.txt
JSFinder2-0.2.dist-info/RECORD
