Metadata-Version: 2.1
Name: JSFinder2
Version: 0.2
Summary: JSFinder2 can be used to find urls and subdomains in JS files.
Author: Richard Schwabe
Maintainer-email: Richard Schwabe <hello@richardschwabe.de>
License: MIT License
Project-URL: Homepage, https://github.com/richardschwabe/JSFinder2/blob/main/README.md
Project-URL: Documentation, https://github.com/richardschwabe/JSFinder2/blob/main/README.md
Project-URL: Bug Tracker, https://github.com/richardschwabe/JSFinder2/issues
Project-URL: Source, https://github.com/richardschwabe/JSFinder2
Classifier: Programming Language :: Python :: 3
Classifier: Programming Language :: Python :: 3 :: Only
Classifier: Programming Language :: Python :: 3.11
Classifier: License :: OSI Approved :: MIT License
Classifier: Operating System :: OS Independent
Requires-Python: >=3.11
License-File: LICENSE
Requires-Dist: anyio ==4.0.0
Requires-Dist: beautifulsoup4 ==4.12.2
Requires-Dist: certifi ==2023.7.22
Requires-Dist: charset-normalizer ==3.2.0
Requires-Dist: filelock ==3.12.4
Requires-Dist: h11 ==0.14.0
Requires-Dist: httpcore ==0.18.0
Requires-Dist: httpx ==0.25.0
Requires-Dist: idna ==3.4
Requires-Dist: requests ==2.31.0
Requires-Dist: requests-file ==1.5.1
Requires-Dist: six ==1.16.0
Requires-Dist: sniffio ==1.3.0
Requires-Dist: soupsieve ==2.5
Requires-Dist: tldextract ==3.5.0
Requires-Dist: urllib3 ==2.0.4
